beacon_snatch/__init__.py
beacon_snatch/authentication.py
beacon_snatch/cli.py
beacon_snatch/content.py
beacon_snatch/helpers.py
beacon_snatch/series.py
beacon_snatch/stream.py
beacon_snatch-0.1.4.dist-info/LICENSE
beacon_snatch-0.1.4.dist-info/METADATA
beacon_snatch-0.1.4.dist-info/WHEEL
beacon_snatch-0.1.4.dist-info/entry_points.txt
beacon_snatch-0.1.4.dist-info/top_level.txt
beacon_snatch-0.1.4.dist-info/RECORD
