Metadata-Version: 2.1
Name: beacon-snatch
Version: 0.1.4
Summary: Snatch from Beacon
Home-page: https://github.com/retrozelda/beacon-snatch
Author: RetroZelda
Author-email: retrozelda@gmail.com
Classifier: Programming Language :: Python :: 3
Classifier: License :: OSI Approved :: MIT License
Classifier: Operating System :: OS Independent
Requires-Python: >=3.6
License-File: LICENSE
Requires-Dist: click ==8.1.7
Requires-Dist: m3u8 ==6.0.0
Requires-Dist: progressbar2 ==4.4.2
Requires-Dist: requests ==2.32.3
Requires-Dist: selenium ==4.23.1
